sqlalchemy_mutables/__init__.py
sqlalchemy_mutables/json_types.py
sqlalchemy_mutables/mutables.py
sqlalchemy_mutables-0.3.1.dist-info/LICENSE
sqlalchemy_mutables-0.3.1.dist-info/METADATA
sqlalchemy_mutables-0.3.1.dist-info/WHEEL
sqlalchemy_mutables-0.3.1.dist-info/top_level.txt
sqlalchemy_mutables-0.3.1.dist-info/RECORD
