Metadata-Version: 2.1
Name: sqlalchemy-mutables
Version: 0.3.1
Summary: Nested mutable SQLAlchemy types. Includes JSON (RFC 7159).
Author: Angelo van Meurs
Project-URL: Homepage, https://github.com/hibuna/sqlalchemy-mutables
Project-URL: Documentation, https://github.com/hibuna/sqlalchemy-mutables/README.md
Classifier: Programming Language :: Python :: 3
Classifier: License :: OSI Approved :: MIT License
Classifier: Operating System :: OS Independent
Requires-Python: >=3.9
License-File: LICENSE
Requires-Dist: SQLAlchemy ==1.3.24
